{"mal_id":171556,"url":"https://myanimelist.net/character/171556/Rin_Nanakura","images":{"jpg":{"image_url":"https://myanimelist.net/images/characters/5/562548.jpg"},"webp":{"image_url":"https://myanimelist.net/images/characters/5/562548.webp","small_image_url":"https://myanimelist.net/images/characters/5/562548t.webp"}},"name":"Rin Nanakura","name_kanji":"七倉 凛","nicknames":[],"favorites":1041,"about":"Hope of the drama club and Eiji's kouhai. She plays various characters and creates a pseudo-harem for her senpai, whom she secretly has feelings for."}